ewoxdbredis/clients/iredis_client.py
ewoxdbredis/clients/redis_cluster_client.py
ewoxdbredis/clients/redis_instance_client.py
ewoxdbredis/connection/db_connection.py
ewoxdbredis/providers/distributed_cache_provider.py
ewoxdbredis/repositories/redis_base_repository.py
ewoxdbredis/repositories/redis_expire_repository.py
ewoxdbredis/repositories/redis_hash_repository.py
ewoxdbredis/repositories/redis_sorted_set_repository.py
ewoxdbredis/settings/connection_settings.py
ewoxdbredis/settings/consumer_settings.py
ewoxdbredis/settings/publisher_settings.py
ewoxdbredis/stream/imessage_stream_publisher.py
ewoxdbredis/stream/message_stream_consumer.py
ewoxdbredis/stream/message_stream_consumer_old.py
ewoxdbredis/stream/message_stream_consumer_old2.py
ewoxdbredis/stream/message_stream_publisher.py
ewoxdbredis-1.2.11.dist-info/METADATA
ewoxdbredis-1.2.11.dist-info/WHEEL
ewoxdbredis-1.2.11.dist-info/licenses/LICENSE
ewoxdbredis-1.2.11.dist-info/RECORD
