Metadata-Version: 2.4
Name: ewoxdbredis
Version: 1.2.11
Summary: 
License-File: LICENSE
Author: Martin Leo Prüss
Author-email: mleopruss@gmail.com
Requires-Python: >=3.9.18, <4.0
Classifier: Programming Language :: Python :: 3
Classifier: Programming Language :: Python :: 3.10
Classifier: Programming Language :: Python :: 3.11
Classifier: Programming Language :: Python :: 3.12
Classifier: Programming Language :: Python :: 3.13
Classifier: Programming Language :: Python :: 3.14
Requires-Dist: ewoxcore (>=1.0.0,<2.0.0)
Requires-Dist: pandas (>=2.3.0,<3.0.0)
Requires-Dist: python-dateutil (>=2.9.0.post0,<3.0.0)
Requires-Dist: python-dotenv (>=1.1.0,<2.0.0)
Requires-Dist: python-i18n (>=0.3.9,<0.4.0)
Requires-Dist: redis (>=6.2.0,<7.0.0)
Requires-Dist: sortedcontainers (>=2.4.0,<3.0.0)
Requires-Dist: tenacity (>=9.1.2,<10.0.0)
